Original_Script.py
Script.py
__init__.py
nonebot_plugin_stupidjdsd-0.0.9.dist-info/LICENSE
nonebot_plugin_stupidjdsd-0.0.9.dist-info/METADATA
nonebot_plugin_stupidjdsd-0.0.9.dist-info/WHEEL
nonebot_plugin_stupidjdsd-0.0.9.dist-info/top_level.txt
nonebot_plugin_stupidjdsd-0.0.9.dist-info/RECORD
