Metadata-Version: 2.1
Name: nonebot-plugin-stupidjdsd
Version: 0.0.9
Summary: 一个笨笨的用于解决广州大学经典诵读任务的插件
Author-email: ShunYu <1265257855@qq.com>
License: GNU AFFERO GENERAL PUBLIC LICENSE
Project-URL: homepage, https://github.com/liu1272/nonebot-plugin-stupidjdsd
Classifier: Programming Language :: Python
Classifier: License :: OSI Approved :: MIT License
Classifier: Operating System :: OS Independent
Requires-Python: >=3.8
License-File: LICENSE
Requires-Dist: requests
Requires-Dist: urllib3
Requires-Dist: nonebot-adapter-onebot
Requires-Dist: nonebot2
